requirements_builder/__init__.py
requirements_builder/cli.py
requirements_builder/requirements_builder.py
requirements_builder/version.py
requirements_builder-0.4.4.dist-info/LICENSE
requirements_builder-0.4.4.dist-info/METADATA
requirements_builder-0.4.4.dist-info/WHEEL
requirements_builder-0.4.4.dist-info/entry_points.txt
requirements_builder-0.4.4.dist-info/top_level.txt
requirements_builder-0.4.4.dist-info/RECORD
