Metadata-Version: 2.1
Name: requirements-builder
Version: 0.4.4
Summary: Build requirements files from setup.py requirements.
Home-page: https://github.com/inveniosoftware/requirements-builder/
Author: Invenio Collaboration
Author-email: info@inveniosoftware.org
License: BSD
Platform: UNKNOWN
Classifier: Intended Audience :: Developers
Classifier: License :: OSI Approved :: BSD License
Classifier: Programming Language :: Python
Classifier: Programming Language :: Python :: 3
Classifier: Programming Language :: Python :: 3.5
Classifier: Programming Language :: Python :: 3.6
Classifier: Programming Language :: Python :: 3.7
Classifier: Programming Language :: Python :: 3.8
Requires-Dist: click (>=7.0)
Requires-Dist: mock (<4,>=1.3.0)
Provides-Extra: all
Requires-Dist: Sphinx (>=3) ; extra == 'all'
Requires-Dist: pytest-invenio (>=1.4.0) ; extra == 'all'
Requires-Dist: pytest-cache (>=1.0) ; extra == 'all'
Provides-Extra: docs
Requires-Dist: Sphinx (>=3) ; extra == 'docs'
